odoo/addons/project_task_material_stock/README.rst
odoo/addons/project_task_material_stock/__init__.py
odoo/addons/project_task_material_stock/__manifest__.py
odoo/addons/project_task_material_stock/data/data.xml
odoo/addons/project_task_material_stock/i18n/ar.po
odoo/addons/project_task_material_stock/i18n/bg.po
odoo/addons/project_task_material_stock/i18n/ca.po
odoo/addons/project_task_material_stock/i18n/da.po
odoo/addons/project_task_material_stock/i18n/de.po
odoo/addons/project_task_material_stock/i18n/el.po
odoo/addons/project_task_material_stock/i18n/el_GR.po
odoo/addons/project_task_material_stock/i18n/es.po
odoo/addons/project_task_material_stock/i18n/es_AR.po
odoo/addons/project_task_material_stock/i18n/es_CR.po
odoo/addons/project_task_material_stock/i18n/es_ES.po
odoo/addons/project_task_material_stock/i18n/es_MX.po
odoo/addons/project_task_material_stock/i18n/es_VE.po
odoo/addons/project_task_material_stock/i18n/fi.po
odoo/addons/project_task_material_stock/i18n/fr.po
odoo/addons/project_task_material_stock/i18n/gl.po
odoo/addons/project_task_material_stock/i18n/hr.po
odoo/addons/project_task_material_stock/i18n/hr_HR.po
odoo/addons/project_task_material_stock/i18n/hu.po
odoo/addons/project_task_material_stock/i18n/it.po
odoo/addons/project_task_material_stock/i18n/ja.po
odoo/addons/project_task_material_stock/i18n/lt.po
odoo/addons/project_task_material_stock/i18n/lv.po
odoo/addons/project_task_material_stock/i18n/mk.po
odoo/addons/project_task_material_stock/i18n/mn.po
odoo/addons/project_task_material_stock/i18n/nb.po
odoo/addons/project_task_material_stock/i18n/nb_NO.po
odoo/addons/project_task_material_stock/i18n/nl.po
odoo/addons/project_task_material_stock/i18n/nl_NL.po
odoo/addons/project_task_material_stock/i18n/pl.po
odoo/addons/project_task_material_stock/i18n/project_task_material_stock.pot
odoo/addons/project_task_material_stock/i18n/pt.po
odoo/addons/project_task_material_stock/i18n/pt_BR.po
odoo12_addon_project_task_material_stock-12.0.1.2.1.dist-info/METADATA
odoo12_addon_project_task_material_stock-12.0.1.2.1.dist-info/WHEEL
odoo12_addon_project_task_material_stock-12.0.1.2.1.dist-info/top_level.txt
odoo12_addon_project_task_material_stock-12.0.1.2.1.dist-info/RECORD
